prexsyn_engine/__init__.py
prexsyn_engine-0.1.1.dev5.dist-info/licenses/LICENSE
prexsyn_engine-0.1.1.dev5.dist-info/METADATA
prexsyn_engine-0.1.1.dev5.dist-info/WHEEL
prexsyn_engine-0.1.1.dev5.dist-info/top_level.txt
prexsyn_engine-0.1.1.dev5.dist-info/RECORD
