Metadata-Version: 2.4
Name: prexsyn-engine
Version: 0.1.1.dev5
Author-email: Shitong Luo <luost26@gmail.com>
Requires-Python: >=3.11
License-File: LICENSE
Dynamic: license-file
